<?xml version="1.0" encoding="UTF-8" standalone="yes"?>
<document xmlns="http://www.abbyy.com/FineReader_xml/FineReader10-schema-v1.xml" version="1.0" producer="ABBYY FineReader Engine 12" languages="" xmlns:xsi="http://www.w3.org/2001/XMLSchema-instance" xsi:schemaLocation="http://www.abbyy.com/FineReader_xml/FineReader10-schema-v1.xml http://www.abbyy.com/FineReader_xml/FineReader10-schema-v1.xml">
<page width="2480" height="3506" resolution="300" originalCoords="1">
<block blockType="Picture" blockName="" l="24" t="105" r="168" b="475"><region><rect l="25" t="105" r="98" b="106"/><rect l="25" t="106" r="168" b="227"/><rect l="24" t="227" r="168" b="230"/><rect l="24" t="230" r="167" b="474"/><rect l="95" t="474" r="167" b="475"/></region>
</block>
<block blockType="Text" blockName="" l="412" t="211" r="943" b="333"><region><rect l="413" t="211" r="479" b="212"/><rect l="413" t="212" r="860" b="213"/><rect l="413" t="213" r="943" b="227"/><rect l="412" t="227" r="943" b="230"/><rect l="412" t="230" r="942" b="331"/><rect l="476" t="331" r="942" b="332"/><rect l="857" t="332" r="942" b="333"/></region>
<text>
<par lineSpacing="1610">
<line baseline="288" l="418" t="217" r="937" b="285"><formatting lang="EnglishUnitedStates">PS FASTENERS&apos;&quot;&#xA;</formatting></line></par>
<par lineSpacing="750">
<line baseline="325" l="418" t="297" r="907" b="327"><formatting lang="EnglishUnitedStates">The Mix-And-Match Expert&#xA;</formatting></line></par>
</text>
</block>
<block blockType="Text" blockName="" l="981" t="121" r="1566" b="301"><region><rect l="982" t="121" r="1241" b="122"/><rect l="982" t="122" r="1566" b="227"/><rect l="981" t="227" r="1566" b="230"/><rect l="981" t="230" r="1565" b="300"/><rect l="1239" t="300" r="1565" b="301"/></region>
<text>
<par lineSpacing="1128">
<line baseline="160" l="989" t="127" r="1447" b="157"><formatting lang="EnglishUnitedStates">PS FASTENERS PTE LTD&#xA;</formatting></line></par>
<par lineSpacing="1128">
<line baseline="206" l="989" t="178" r="1560" b="209"><formatting lang="EnglishUnitedStates">No. 9 Tampines Industrial Drive, #01-03</formatting></line>
<line baseline="252" l="988" t="224" r="1250" b="255"><formatting lang="EnglishUnitedStates">Singapore 528543&#xA;</formatting></line></par>
<par lineSpacing="1128">
<line baseline="297" l="987" t="269" r="1506" b="295"><formatting lang="EnglishUnitedStates">T +65 6747 7080 F +65 6742 0642&#xA;</formatting></line></par>
</text>
</block>
<block blockType="Text" blockName="" l="1718" t="327" r="2210" b="457"><region><rect l="1718" t="327" r="2004" b="328"/><rect l="1718" t="328" r="2210" b="456"/><rect l="2001" t="456" r="2210" b="457"/></region>
<text>
<par lineSpacing="2640">
<line baseline="427" l="1724" t="333" r="2204" b="452"><formatting lang="EnglishUnitedStates">WEM 8966&#xA;</formatting></line></par>
</text>
</block>
<block blockType="Text" blockName="" l="981" t="309" r="1772" b="405"><region><rect l="981" t="309" r="1241" b="310"/><rect l="981" t="310" r="1623" b="311"/><rect l="981" t="311" r="1772" b="354"/><rect l="981" t="354" r="1730" b="403"/><rect l="1239" t="403" r="1730" b="404"/><rect l="1620" t="404" r="1730" b="405"/></region>
<text>
<par lineSpacing="860">
<line baseline="343" l="987" t="315" r="1765" b="347"><formatting lang="EnglishUnitedStates">E sales@psfasteners.com W www.psfasteners.com&#xA;</formatting></line></par>
<par lineSpacing="630">
<line baseline="396" l="986" t="373" r="1729" b="398"><formatting lang="EnglishUnitedStates">Co. Reg, No. 199102937E GST Reg. No. M2-0100203-6 1&#xA;</formatting></line></par>
</text>
</block>
<block blockType="Picture" blockName="" l="2245" t="128" r="2455" b="282"><region><rect l="2246" t="128" r="2385" b="129"/><rect l="2246" t="129" r="2455" b="227"/><rect l="2245" t="227" r="2455" b="230"/><rect l="2245" t="230" r="2454" b="281"/><rect l="2382" t="281" r="2454" b="282"/></region>
</block>
<block blockType="Text" blockName="" l="311" t="510" r="1278" b="861"><region><rect l="312" t="510" r="479" b="511"/><rect l="312" t="511" r="860" b="512"/><rect l="312" t="512" r="1241" b="513"/><rect l="312" t="513" r="1278" b="608"/><rect l="311" t="608" r="1278" b="611"/><rect l="311" t="611" r="1277" b="858"/><rect l="476" t="858" r="1277" b="859"/><rect l="857" t="859" r="1277" b="860"/><rect l="1239" t="860" r="1277" b="861"/></region>
<text>
<par lineSpacing="1380">
<line baseline="565" l="323" t="517" r="645" b="560"><formatting lang="EnglishUnitedStates">CUSTOMER:&#xA;</formatting></line></par>
<par lineSpacing="1332">
<line baseline="636" l="317" t="599" r="1148" b="633"><formatting lang="EnglishUnitedStates">YEW S1ONG INDUSTRIAL SUPPLIES SDN BHD</formatting></line>
<line baseline="691" l="320" t="655" r="1138" b="696"><formatting lang="EnglishUnitedStates">SUBLOT 13 &amp; 14,(LOT 552), JALAN SUBANG 2</formatting></line>
<line baseline="746" l="318" t="710" r="1271" b="748"><formatting lang="EnglishUnitedStates">SUNGAI PENAGA INDUSTRIAL PARK, SUBANG JAYA,&#xA;</formatting></line></par>
<par lineSpacing="1332">
<line baseline="801" l="320" t="765" r="957" b="802"><formatting lang="EnglishUnitedStates">47500 PETALING JAYA, SELANGOR&#xA;</formatting></line></par>
<par lineSpacing="1332">
<line baseline="857" l="319" t="821" r="502" b="853"><formatting lang="EnglishUnitedStates">MALAYSIA&#xA;</formatting></line></par>
</text>
</block>
<block blockType="Text" blockName="" l="1962" t="511" r="2303" b="566"><region><rect l="1962" t="511" r="2004" b="512"/><rect l="1962" t="512" r="2303" b="565"/><rect l="2001" t="565" r="2303" b="566"/></region>
<text>
<par align="Center" lineSpacing="1380">
<line baseline="560" l="1968" t="517" r="2297" b="559"><formatting lang="EnglishUnitedStates">TAX INVOICE&#xA;</formatting></line></par>
</text>
</block>
<block blockType="Text" blockName="" l="1789" t="597" r="2086" b="871"><region><rect l="1790" t="597" r="2004" b="598"/><rect l="1790" t="598" r="2086" b="608"/><rect l="1789" t="608" r="2086" b="611"/><rect l="1789" t="611" r="2085" b="870"/><rect l="2001" t="870" r="2085" b="871"/></region>
<text>
<par align="Right" lineSpacing="1344">
<line baseline="635" l="2029" t="604" r="2078" b="634"><formatting lang="EnglishUnitedStates">No&#xA;</formatting></line></par>
<par align="Right" lineSpacing="1344">
<line baseline="689" l="1795" t="658" r="2079" b="690"><formatting lang="EnglishUnitedStates">Customer Code</formatting></line>
<line baseline="744" l="1852" t="713" r="2077" b="745"><formatting lang="EnglishUnitedStates">Invoice Date</formatting></line>
<line baseline="801" l="1968" t="770" r="2079" b="801"><formatting lang="EnglishUnitedStates">Terms&#xA;</formatting></line></par>
<par align="Right" lineSpacing="1344">
<line baseline="857" l="1910" t="827" r="2078" b="865"><formatting lang="EnglishUnitedStates">Currency&#xA;</formatting></line></par>
</text>
</block>
<block blockType="Text" blockName="" l="2121" t="598" r="2341" b="863"><region><rect l="2122" t="598" r="2340" b="599"/><rect l="2122" t="599" r="2341" b="608"/><rect l="2121" t="608" r="2341" b="611"/><rect l="2121" t="611" r="2340" b="863"/></region>
<text>
<par lineSpacing="1030">
<line baseline="634" l="2141" t="604" r="2334" b="634"><formatting lang="EnglishUnitedStates">519020285&#xA;</formatting></line></par>
<par lineSpacing="1030">
<line baseline="689" l="2142" t="658" r="2254" b="688"><formatting lang="EnglishUnitedStates">SY005&#xA;</formatting></line></par>
<par lineSpacing="1030">
<line baseline="743" l="2127" t="713" r="2317" b="743"><formatting lang="EnglishUnitedStates">25/02/2019&#xA;</formatting></line></par>
<par lineSpacing="1030">
<line baseline="800" l="2143" t="770" r="2295" b="800"><formatting lang="EnglishUnitedStates">30 DAYS&#xA;</formatting></line></par>
<par lineSpacing="1030">
<line baseline="858" l="2140" t="827" r="2222" b="857"><formatting lang="EnglishUnitedStates">SGD&#xA;</formatting></line></par>
</text>
</block>
<block blockType="Table" blockName="" l="342" t="925" r="2357" b="1477"><region><rect l="344" t="925" r="479" b="926"/><rect l="344" t="926" r="860" b="927"/><rect l="344" t="927" r="1241" b="928"/><rect l="344" t="928" r="1623" b="929"/><rect l="344" t="929" r="2004" b="930"/><rect l="344" t="930" r="2356" b="931"/><rect l="344" t="931" r="2357" b="989"/><rect l="343" t="989" r="2357" b="992"/><rect l="343" t="992" r="2356" b="1370"/><rect l="342" t="1370" r="2356" b="1373"/><rect l="342" t="1373" r="2355" b="1472"/><rect l="476" t="1472" r="2355" b="1473"/><rect l="857" t="1473" r="2355" b="1474"/><rect l="1239" t="1474" r="2355" b="1475"/><rect l="1620" t="1475" r="2355" b="1476"/><rect l="2001" t="1476" r="2355" b="1477"/></region>
<row>
<cell rowSpan="2" leftBorder="White" topBorder="White" rightBorder="White" width="1062" height="114">
<text>
<par startIndent="1600" lineSpacing="1030">
<line baseline="1028" l="414" t="991" r="625" b="1030"><formatting lang="EnglishUnitedStates">Description&#xA;</formatting></line></par>
</text></cell>
<cell rowSpan="2" leftBorder="White" topBorder="White" rightBorder="White" width="171" height="114">
<text>
<par align="Right" lineSpacing="1030">
<line baseline="1030" l="1451" t="996" r="1564" b="1034"><formatting lang="EnglishUnitedStates">Origin&#xA;</formatting></line></par>
</text></cell>
<cell rowSpan="2" leftBorder="White" topBorder="White" rightBorder="White" width="188" height="114">
<text>
<par align="Right" lineSpacing="1030">
<line baseline="968" l="1589" t="936" r="1747" b="975"><formatting lang="EnglishUnitedStates">Quantity&#xA;</formatting></line></par>
<par align="Right" lineSpacing="1030">
<line baseline="1022" l="1640" t="990" r="1745" b="1028"><formatting lang="EnglishUnitedStates">(PCS)&#xA;</formatting></line></par>
</text></cell>
<cell rowSpan="2" leftBorder="White" topBorder="White" rightBorder="White" width="155" height="114">
<text>
<par align="Right" lineSpacing="1030">
<line baseline="969" l="1771" t="937" r="1900" b="975"><formatting lang="EnglishUnitedStates">Weight&#xA;</formatting></line></par>
<par align="Right" lineSpacing="1030">
<line baseline="1022" l="1781" t="990" r="1890" b="1029"><formatting lang="EnglishUnitedStates">(KGS)&#xA;</formatting></line></par>
</text></cell>
<cell colSpan="2" leftBorder="White" topBorder="White" rightBorder="White" bottomBorder="White" width="437" height="53">
<text>
<par lineSpacing="1030">
<line baseline="968" l="1930" t="936" r="2109" b="968"><formatting lang="EnglishUnitedStates">Unit Price&#xA;</formatting></line></par>
</text></cell></row>
<row>
<cell leftBorder="White" topBorder="White" rightBorder="White" width="266" height="61">
<text>
<par startIndent="1600" lineSpacing="1030">
<line baseline="1031" l="1996" t="987" r="2043" b="1030"><formatting lang="EnglishUnitedStates">($)&#xA;</formatting></line></par>
</text></cell>
<cell leftBorder="White" topBorder="White" rightBorder="White" width="171" height="61">
<text>
<par align="Right" lineSpacing="1030">
<line baseline="1022" l="2214" t="989" r="2340" b="1023"><formatting lang="EnglishUnitedStates">Total $&#xA;</formatting></line></par>
</text></cell></row>
<row>
<cell leftBorder="White" rightBorder="White" bottomBorder="White" width="1062" height="78">
<text>
<par lineSpacing="1030">
<line baseline="1109" l="368" t="1073" r="1359" b="1107"><formatting lang="EnglishUnitedStates">1 SS 304 SOCKET FLAT HD CAP SCREW UNC M 6 X 50&#xA;</formatting></line></par>
</text></cell>
<cell leftBorder="White" rightBorder="White" bottomBorder="White" width="171" height="78">
<text>
<par align="Right" lineSpacing="1030">
<line baseline="1110" l="1478" t="1076" r="1537" b="1107"><formatting lang="EnglishUnitedStates">TW&#xA;</formatting></line></par>
</text></cell>
<cell leftBorder="White" rightBorder="White" bottomBorder="White" width="188" height="78">
<text>
<par align="Right" lineSpacing="1030">
<line baseline="1109" l="1702" t="1077" r="1744" b="1107"><formatting lang="EnglishUnitedStates">50&#xA;</formatting></line></par>
</text></cell>
<cell leftBorder="White" rightBorder="White" bottomBorder="White" width="155" height="78">
<text>
<par align="Right" lineSpacing="1030">
<line baseline="1110" l="1891" t="1078" r="1903" b="1108"><formatting lang="EnglishUnitedStates">1&#xA;</formatting></line></par>
</text></cell>
<cell leftBorder="White" rightBorder="White" bottomBorder="White" width="266" height="78">
<text>
<par startIndent="1600" lineSpacing="1030">
<line baseline="1110" l="1994" t="1078" r="2109" b="1109"><formatting lang="EnglishUnitedStates">3.1600&#xA;</formatting></line></par>
</text></cell>
<cell leftBorder="White" rightBorder="White" bottomBorder="White" width="171" height="78">
<text>
<par align="Right" lineSpacing="1030">
<line baseline="1110" l="2266" t="1079" r="2339" b="1109"><formatting lang="EnglishUnitedStates">3.16&#xA;</formatting></line></par>
</text></cell></row>
<row>
<cell leftBorder="White" topBorder="White" rightBorder="White" bottomBorder="White" width="1062" height="58">
<text>
<par lineSpacing="1030">
<line baseline="1167" l="362" t="1131" r="1294" b="1165"><formatting lang="EnglishUnitedStates">2 SS MACHINE SCREW CSK PHIL HD UNC M 6 X 50&#xA;</formatting></line></par>
</text></cell>
<cell leftBorder="White" topBorder="White" rightBorder="White" bottomBorder="White" width="171" height="58">
<text>
<par startIndent="1600" lineSpacing="1030">
<line baseline="1167" l="1475" t="1135" r="1537" b="1165"><formatting lang="EnglishUnitedStates">TW&#xA;</formatting></line></par>
</text></cell>
<cell leftBorder="White" topBorder="White" rightBorder="White" bottomBorder="White" width="188" height="58">
<text>
<par align="Right" lineSpacing="1030">
<line baseline="1168" l="1657" t="1135" r="1742" b="1166"><formatting lang="EnglishUnitedStates">3350&#xA;</formatting></line></par>
</text></cell>
<cell leftBorder="White" topBorder="White" rightBorder="White" bottomBorder="White" width="155" height="58">
<text>
<par align="Right" lineSpacing="1030">
<line baseline="1168" l="1864" t="1136" r="1906" b="1166"><formatting lang="EnglishUnitedStates">40&#xA;</formatting></line></par>
</text></cell>
<cell leftBorder="White" topBorder="White" rightBorder="White" bottomBorder="White" width="266" height="58">
<text>
<par startIndent="1600" lineSpacing="1030">
<line baseline="1167" l="1992" t="1135" r="2106" b="1167"><formatting lang="EnglishUnitedStates">5.7553&#xA;</formatting></line></par>
</text></cell>
<cell leftBorder="White" topBorder="White" rightBorder="White" bottomBorder="White" width="171" height="58">
<text>
<par align="Right" lineSpacing="1030">
<line baseline="1167" l="2220" t="1136" r="2331" b="1167"><formatting lang="EnglishUnitedStates">230.21&#xA;</formatting></line></par>
</text></cell></row>
<row>
<cell leftBorder="White" topBorder="White" rightBorder="White" bottomBorder="White" width="1062" height="59">
<text>
<par lineSpacing="1030">
<line baseline="1226" l="364" t="1189" r="1189" b="1223"><formatting lang="EnglishUnitedStates">3 SS A 2 HEX NUT LEFT HAND THREAD M 8 L&#xA;</formatting></line></par>
</text></cell>
<cell leftBorder="White" topBorder="White" rightBorder="White" bottomBorder="White" width="171" height="59">
<text>
<par startIndent="1600" lineSpacing="1030">
<line baseline="1225" l="1477" t="1193" r="1538" b="1223"><formatting lang="EnglishUnitedStates">TW&#xA;</formatting></line></par>
</text></cell>
<cell leftBorder="White" topBorder="White" rightBorder="White" bottomBorder="White" width="188" height="59">
<text>
<par align="Right" lineSpacing="1030">
<line baseline="1225" l="1679" t="1194" r="1743" b="1223"><formatting lang="EnglishUnitedStates">300&#xA;</formatting></line></par>
</text></cell>
<cell leftBorder="White" topBorder="White" rightBorder="White" bottomBorder="White" width="155" height="59">
<text>
<par align="Right" lineSpacing="1030">
<line baseline="1226" l="1887" t="1194" r="1906" b="1224"><formatting lang="EnglishUnitedStates">2&#xA;</formatting></line></par>
</text></cell>
<cell leftBorder="White" topBorder="White" rightBorder="White" bottomBorder="White" width="266" height="59">
<text>
<par startIndent="1600" lineSpacing="1030">
<line baseline="1225" l="1994" t="1193" r="2108" b="1225"><formatting lang="EnglishUnitedStates">6.9350&#xA;</formatting></line></par>
</text></cell>
<cell leftBorder="White" topBorder="White" rightBorder="White" bottomBorder="White" width="171" height="59">
<text>
<par align="Right" lineSpacing="1030">
<line baseline="1225" l="2247" t="1194" r="2338" b="1224"><formatting lang="EnglishUnitedStates">13.87&#xA;</formatting></line></par>
</text></cell></row>
<row>
<cell leftBorder="White" topBorder="White" rightBorder="White" bottomBorder="White" width="1062" height="57">
<text>
<par lineSpacing="1030">
<line baseline="1283" l="362" t="1247" r="1208" b="1280"><formatting lang="EnglishUnitedStates">4 SS A 2 HEX NUT LEFT HAND THREAD M 10 L&#xA;</formatting></line></par>
</text></cell>
<cell leftBorder="White" topBorder="White" rightBorder="White" bottomBorder="White" width="171" height="57">
<text>
<par align="Right" rightIndent="800" lineSpacing="1030">
<line baseline="1284" l="1475" t="1251" r="1536" b="1281"><formatting lang="EnglishUnitedStates">TW&#xA;</formatting></line></par>
</text></cell>
<cell leftBorder="White" topBorder="White" rightBorder="White" bottomBorder="White" width="188" height="57">
<text>
<par align="Right" lineSpacing="1030">
<line baseline="1283" l="1679" t="1252" r="1741" b="1281"><formatting lang="EnglishUnitedStates">200&#xA;</formatting></line></par>
</text></cell>
<cell leftBorder="White" topBorder="White" rightBorder="White" bottomBorder="White" width="155" height="57">
<text>
<par align="Right" lineSpacing="1030">
<line baseline="1283" l="1884" t="1252" r="1904" b="1281"><formatting lang="EnglishUnitedStates">2&#xA;</formatting></line></par>
</text></cell>
<cell leftBorder="White" topBorder="White" rightBorder="White" bottomBorder="White" width="266" height="57">
<text>
<par startIndent="1600" lineSpacing="1030">
<line baseline="1284" l="1992" t="1252" r="2107" b="1283"><formatting lang="EnglishUnitedStates">9.8100&#xA;</formatting></line></par>
</text></cell>
<cell leftBorder="White" topBorder="White" rightBorder="White" bottomBorder="White" width="171" height="57">
<text>
<par align="Right" lineSpacing="1030">
<line baseline="1282" l="2245" t="1252" r="2336" b="1282"><formatting lang="EnglishUnitedStates">19.62&#xA;</formatting></line></par>
</text></cell></row>
<row>
<cell leftBorder="White" topBorder="White" rightBorder="White" bottomBorder="White" width="1062" height="113">
<text>
<par lineSpacing="1030">
<line baseline="1340" l="363" t="1303" r="1092" b="1337"><formatting lang="EnglishUnitedStates">5 HT HEX BOLT GR‘8.8 DIN 933 M 5 X 10&#xA;</formatting></line></par>
</text></cell>
<cell leftBorder="White" topBorder="White" rightBorder="White" bottomBorder="White" width="171" height="113">
<text>
<par align="Right" rightIndent="800" lineSpacing="1030">
<line baseline="1341" l="1476" t="1308" r="1537" b="1338"><formatting lang="EnglishUnitedStates">TW&#xA;</formatting></line></par>
</text></cell>
<cell leftBorder="White" topBorder="White" rightBorder="White" bottomBorder="White" width="188" height="113">
<text>
<par align="Right" lineSpacing="1030">
<line baseline="1340" l="1659" t="1308" r="1744" b="1339"><formatting lang="EnglishUnitedStates">2490&#xA;</formatting></line></par>
</text></cell>
<cell leftBorder="White" topBorder="White" rightBorder="White" width="155" height="113">
<text>
<par align="Right" lineSpacing="1030">
<line baseline="1341" l="1887" t="1309" r="1907" b="1339"><formatting lang="EnglishUnitedStates">6&#xA;</formatting></line></par>
</text></cell>
<cell leftBorder="White" topBorder="White" rightBorder="White" width="266" height="113">
<text>
<par startIndent="1600" lineSpacing="1030">
<line baseline="1340" l="1993" t="1307" r="2109" b="1340"><formatting lang="EnglishUnitedStates">3.6650&#xA;</formatting></line></par>
</text></cell>
<cell leftBorder="White" topBorder="White" rightBorder="White" width="171" height="113">
<text>
<par align="Right" lineSpacing="1030">
<line baseline="1340" l="2243" t="1309" r="2337" b="1339"><formatting lang="EnglishUnitedStates">21.99&#xA;</formatting></line></par>
</text></cell></row>
<row>
<cell leftBorder="White" topBorder="White" rightBorder="White" bottomBorder="White" width="1062" height="68">
<text>
<par lineSpacing="1030"></par>
</text></cell>
<cell leftBorder="White" topBorder="White" rightBorder="White" bottomBorder="White" width="171" height="68">
<text>
<par leftIndent="1000" lineSpacing="1030"></par>
</text></cell>
<cell leftBorder="White" topBorder="White" rightBorder="White" bottomBorder="White" width="188" height="68">
<text>
<par align="Right" lineSpacing="1030">
<line baseline="1445" l="1610" t="1411" r="1738" b="1445"><formatting lang="EnglishUnitedStates">TOTAL:&#xA;</formatting></line></par>
</text></cell>
<cell leftBorder="White" rightBorder="White" width="155" height="68">
<text>
<par align="Right" rightIndent="1600" lineSpacing="1030">
<line baseline="1445" l="1810" t="1413" r="1848" b="1443"><formatting lang="EnglishUnitedStates">51&#xA;</formatting></line></par>
</text></cell>
<cell leftBorder="White" rightBorder="White" bottomBorder="White" width="266" height="68">
<text>
<par align="Right" lineSpacing="1030">
<line baseline="1456" l="2144" t="1420" r="2163" b="1455"><formatting lang="EnglishUnitedStates">$&#xA;</formatting></line></par>
</text></cell>
<cell leftBorder="White" rightBorder="White" bottomBorder="White" width="171" height="68">
<text>
<par align="Center" lineSpacing="1030">
<line baseline="1452" l="2205" t="1422" r="2321" b="1452"><formatting lang="EnglishUnitedStates">288.85&#xA;</formatting></line></par>
</text></cell></row>
</block>
<block blockType="Text" blockName="" l="389" t="1986" r="1189" b="2290"><region><rect l="390" t="1986" r="479" b="1987"/><rect l="390" t="1987" r="860" b="1988"/><rect l="390" t="1988" r="1189" b="2133"/><rect l="389" t="2133" r="1189" b="2136"/><rect l="389" t="2136" r="1188" b="2288"/><rect l="476" t="2288" r="1188" b="2289"/><rect l="857" t="2289" r="1188" b="2290"/></region>
<text>
<par startIndent="1200" lineSpacing="1030">
<line baseline="2028" l="399" t="1992" r="745" b="2024"><formatting lang="EnglishUnitedStates">MATERIAL: STEEL&#xA;</formatting></line></par>
<par startIndent="1200" lineSpacing="1030">
<line baseline="2085" l="396" t="2049" r="694" b="2081"><formatting lang="EnglishUnitedStates">TOTAL: 7 CTNS&#xA;</formatting></line></par>
<par startIndent="1200" lineSpacing="1030">
<line baseline="2157" l="398" t="2120" r="631" b="2153"><formatting lang="EnglishUnitedStates">DELIVER TO:&#xA;</formatting></line></par>
<par startIndent="1200" lineSpacing="1030">
<line baseline="2225" l="397" t="2190" r="975" b="2227"><formatting lang="EnglishUnitedStates">RIZAL TRADING &amp; TRANSPORT,&#xA;</formatting></line></par>
<par startIndent="1200" lineSpacing="1030">
<line baseline="2282" l="397" t="2246" r="1182" b="2284"><formatting lang="EnglishUnitedStates">NOBLE WAREHOUSE, SINGAPORE 347796&#xA;</formatting></line></par>
</text>
</block>
<block blockType="Picture" blockName="" l="1747" t="1991" r="2266" b="2225"><region><rect l="1748" t="1991" r="2004" b="1992"/><rect l="1748" t="1992" r="2266" b="2133"/><rect l="1747" t="2133" r="2266" b="2136"/><rect l="1747" t="2136" r="2265" b="2224"/><rect l="2001" t="2224" r="2265" b="2225"/></region>
</block>
<block blockType="Text" blockName="" l="1320" t="3194" r="1486" b="3236"><region><rect l="1320" t="3194" r="1486" b="3236"/></region>
<text>
<par align="Center" lineSpacing="800">
<line baseline="3227" l="1326" t="3200" r="1480" b="3230"><formatting lang="EnglishUnitedStates">Page 1 of 1&#xA;</formatting></line></par>
</text>
</block>
<block blockType="Separator" blockName="" l="2250" t="132" r="2449" b="137"><region><rect l="2250" t="132" r="2385" b="133"/><rect l="2250" t="133" r="2449" b="136"/><rect l="2382" t="136" r="2449" b="137"/></region>
<separator type="Black" thickness="4"><start x="2250" y="135"/><end x="2449" y="135"/>
</separator>
</block>
<block blockType="Separator" blockName="" l="2259" t="239" r="2351" b="243"><region><rect l="2260" t="239" r="2321" b="240"/><rect l="2259" t="240" r="2351" b="242"/><rect l="2321" t="242" r="2351" b="243"/></region>
<separator type="Black" thickness="3"><start x="2260" y="242"/><end x="2352" y="242"/>
</separator>
</block>
<block blockType="Separator" blockName="" l="2248" t="274" r="2448" b="278"><region><rect l="2248" t="274" r="2385" b="275"/><rect l="2248" t="275" r="2448" b="277"/><rect l="2382" t="277" r="2448" b="278"/></region>
<separator type="Black" thickness="3"><start x="2249" y="276"/><end x="2449" y="276"/>
</separator>
</block>
<block blockType="Separator" blockName="" l="1914" t="499" r="2350" b="505"><region><rect l="1914" t="499" r="2349" b="500"/><rect l="1914" t="500" r="2350" b="504"/><rect l="2001" t="504" r="2325" b="505"/></region>
<separator type="Black" thickness="5"><start x="1915" y="503"/><end x="2351" y="503"/>
</separator>
</block>
<block blockType="Separator" blockName="" l="1916" t="577" r="2352" b="583"><region><rect l="1916" t="577" r="2351" b="578"/><rect l="1916" t="578" r="2352" b="582"/><rect l="2001" t="582" r="2288" b="583"/></region>
<separator type="Black" thickness="5"><start x="1917" y="581"/><end x="2353" y="581"/>
</separator>
</block>
<block blockType="Separator" blockName="" l="306" t="1034" r="2346" b="1050"><region><rect l="306" t="1034" r="479" b="1035"/><rect l="306" t="1035" r="860" b="1036"/><rect l="306" t="1036" r="1241" b="1037"/><rect l="306" t="1037" r="1411" b="1038"/><rect l="306" t="1038" r="1623" b="1039"/><rect l="306" t="1039" r="2004" b="1040"/><rect l="306" t="1040" r="2346" b="1043"/><rect l="476" t="1043" r="2346" b="1044"/><rect l="857" t="1044" r="2346" b="1045"/><rect l="881" t="1045" r="2346" b="1046"/><rect l="1239" t="1046" r="2346" b="1047"/><rect l="1411" t="1047" r="2346" b="1048"/><rect l="1620" t="1048" r="2346" b="1049"/><rect l="2001" t="1049" r="2346" b="1050"/></region>
<separator type="Black" thickness="9"><start x="309" y="1045"/><end x="2349" y="1045"/>
</separator>
</block>
<block blockType="Separator" blockName="" l="2114" t="1407" r="2345" b="1412"><region><rect l="2114" t="1407" r="2345" b="1411"/><rect l="2115" t="1411" r="2345" b="1412"/></region>
<separator type="Black" thickness="4"><start x="2118" y="1410"/><end x="2349" y="1410"/>
</separator>
</block>
<block blockType="Separator" blockName="" l="1749" t="1407" r="1915" b="1411"><region><rect l="1749" t="1407" r="1915" b="1411"/></region>
<separator type="Black" thickness="4"><start x="1753" y="1411"/><end x="1919" y="1411"/>
</separator>
</block>
<block blockType="Separator" blockName="" l="1752" t="1463" r="1916" b="1472"><region><rect l="1870" t="1463" r="1882" b="1464"/><rect l="1752" t="1464" r="1916" b="1468"/><rect l="1752" t="1468" r="1907" b="1469"/><rect l="1800" t="1469" r="1916" b="1470"/><rect l="1752" t="1470" r="1916" b="1472"/></region>
<separator type="Black" thickness="6"><start x="1756" y="1469"/><end x="1920" y="1469"/>
</separator>
</block>
<block blockType="Separator" blockName="" l="1747" t="2179" r="2114" b="2185"><region><rect l="1747" t="2179" r="2004" b="2180"/><rect l="1747" t="2180" r="2114" b="2184"/><rect l="2001" t="2184" r="2114" b="2185"/></region>
<separator type="Black" thickness="5"><start x="1753" y="2183"/><end x="2120" y="2183"/>
</separator>
</block>
<block blockType="Separator" blockName="" l="0" t="653" r="4" b="1617"><region><rect l="1" t="653" r="4" b="654"/><rect l="0" t="654" r="4" b="992"/><rect l="0" t="992" r="3" b="1373"/><rect l="0" t="1373" r="2" b="1617"/></region>
<separator type="Black" thickness="2"><start x="4" y="660"/><end x="4" y="1624"/>
</separator>
</block>
<block blockType="Separator" blockName="" l="2249" t="132" r="2253" b="277"><region><rect l="2250" t="132" r="2253" b="227"/><rect l="2249" t="227" r="2253" b="230"/><rect l="2249" t="230" r="2252" b="277"/></region>
<separator type="Black" thickness="3"><start x="2251" y="133"/><end x="2251" y="278"/>
</separator>
</block>
<block blockType="Separator" blockName="" l="2365" t="143" r="2369" b="263"><region><rect l="2366" t="143" r="2368" b="144"/><rect l="2366" t="144" r="2369" b="227"/><rect l="2365" t="227" r="2369" b="230"/><rect l="2365" t="230" r="2368" b="263"/></region>
<separator type="Black" thickness="3"><start x="2367" y="144"/><end x="2367" y="264"/>
</separator>
</block>
<block blockType="Separator" blockName="" l="2346" t="500" r="2352" b="582"><region><rect l="2346" t="500" r="2350" b="501"/><rect l="2346" t="501" r="2351" b="540"/><rect l="2347" t="540" r="2351" b="541"/><rect l="2348" t="541" r="2352" b="582"/></region>
<separator type="Black" thickness="4"><start x="2350" y="501"/><end x="2350" y="583"/>
</separator>
</block>
<block blockType="Separator" blockName="" l="1756" t="1406" r="1838" b="1411"><region><rect l="1756" t="1406" r="1838" b="1411"/></region>
<separator type="Dotted" thickness="5"><start x="1760" y="1410"/><end x="1842" y="1410"/>
</separator>
</block>
<block blockType="Separator" blockName="" l="2090" t="613" r="2099" b="857"><region><rect l="2090" t="613" r="2099" b="857"/></region>
<separator type="Dotted" thickness="7"><start x="2096" y="614"/><end x="2096" y="858"/>
</separator>
</block>
</page>
</document>